{
    "_links": {
        "self": {
            "href": ""
        },
        "type": {
            "href": "http:\/\/drupal.org\/rest\/type\/paragraph\/stanford_wysiwyg"
        }
    },
    "uuid": [
        {
            "value": "f948f4d8-9345-46f3-86a0-4b845f38b85c"
        }
    ],
    "langcode": [
        {
            "value": "en",
            "lang": "en"
        }
    ],
    "type": [
        {
            "target_id": "stanford_wysiwyg"
        }
    ],
    "status": [
        {
            "value": true,
            "lang": "en"
        }
    ],
    "created": [
        {
            "value": "2020-04-17T05:53:01+00:00",
            "lang": "en",
            "format": "Y-m-d\\TH:i:sP"
        }
    ],
    "parent_id": [
        {
            "value": "fbd6c70d-fab6-4aae-956f-2df92610fad6"
        }
    ],
    "parent_type": [
        {
            "value": "node"
        }
    ],
    "parent_field_name": [
        {
            "value": "su_news_components"
        }
    ],
    "behavior_settings": [
        {
            "value": []
        }
    ],
    "default_langcode": [
        {
            "value": true,
            "lang": "en"
        }
    ],
    "su_wysiwyg_text": [
        {
            "value": "<p>Smith Lecture is proin lacus lacus, eleifend tristique volutpat vitae, mattis nec nisl. Class aptent taciti sociosqu ad litora torquent per conubia nostra, per inceptos himenaeos.<\/p>\r\n\r\n<div>&nbsp;<\/div>\r\n",
            "format": "stanford_html",
            "processed": "<p>Smith Lecture is proin lacus lacus, eleifend tristique volutpat vitae, mattis nec nisl. Class aptent taciti sociosqu ad litora torquent per conubia nostra, per inceptos himenaeos.<\/p>\n\n<div>\u00a0<\/div>"
        }
    ]
}
